setup.py
look_up.egg-info/PKG-INFO
look_up.egg-info/SOURCES.txt
look_up.egg-info/dependency_links.txt
look_up.egg-info/entry_points.txt
look_up.egg-info/requires.txt
look_up.egg-info/top_level.txt
lookup/__init__.py
lookup/__main__.py
lookup/look.py