Metadata-Version: 1.0
Name: look-up
Version: 0.1.1
Summary: Get the meaning of a word on your terminal
Home-page: https://github.com/Dineshs91/lookup
Author: Dinesh S
Author-email: dineshpy07@gmail.com
License: MIT
Keywords: english dictionary words
Platform: UNKNOWN
